nationwide/__init__.py
nationwide-0.0.1.dist-info/LICENCE
nationwide-0.0.1.dist-info/METADATA
nationwide-0.0.1.dist-info/WHEEL
nationwide-0.0.1.dist-info/top_level.txt
nationwide-0.0.1.dist-info/RECORD
