Metadata-Version: 2.1
Name: nationwide
Version: 0.0.1
Summary: Python Package for Nationwide API integration
Home-page: https://linkedin.com/in/joetilsed/
Author: Joe Tilsed
Author-email: Joe@Tilsed.com
License: UNKNOWN
Keywords: nationwide python api
Platform: UNKNOWN
Classifier: Programming Language :: Python :: 3
Classifier: License :: OSI Approved :: MIT License
Classifier: Operating System :: OS Independent
